pigeonly_address/__init__.py
pigeonly_address/address.py
pigeonly_address/usps/__init__.py
pigeonly_address/usps/address.py
pigeonly_address/usps/client.py
pigeonly_address-0.0.1.dist-info/LICENSE
pigeonly_address-0.0.1.dist-info/METADATA
pigeonly_address-0.0.1.dist-info/WHEEL
pigeonly_address-0.0.1.dist-info/top_level.txt
pigeonly_address-0.0.1.dist-info/RECORD
