Metadata-Version: 2.1
Name: pigeonly-address
Version: 0.0.1
Summary: Address Standardization
Author-email: Peter Flynn <peterflynn@pigeon.ly>
License: MIT License        
Project-URL: Homepage, https://gitlab.pigeon.ly/pflynn/pigeonly-address
Keywords: address
Classifier: License :: OSI Approved :: MIT License
Classifier: Programming Language :: Python
Classifier: Programming Language :: Python :: 3
Requires-Python: >=3.6
License-File: LICENSE
Requires-Dist: lxml
Requires-Dist: xmltodict
Requires-Dist: requests
Provides-Extra: dev
Requires-Dist: black ; extra == 'dev'
Requires-Dist: isort ; extra == 'dev'
Requires-Dist: flake8 ; extra == 'dev'
Requires-Dist: radon ; extra == 'dev'
Requires-Dist: pre-commit ; extra == 'dev'
Requires-Dist: pytest ; extra == 'dev'
Requires-Dist: pytest-mock ; extra == 'dev'
